faculty_models.py
faculty_models-0.2.0.dist-info/LICENSE-2.0.txt
faculty_models-0.2.0.dist-info/METADATA
faculty_models-0.2.0.dist-info/WHEEL
faculty_models-0.2.0.dist-info/top_level.txt
faculty_models-0.2.0.dist-info/RECORD
