Metadata-Version: 2.1
Name: faculty-models
Version: 0.2.0
Summary: Python library for retrieving models from Faculty platform.
Home-page: https://faculty.ai/products-services/platform/
Author: Faculty
Author-email: opensource@faculty.ai
License: Apache Software License
Platform: UNKNOWN
Requires-Dist: faculty (>=0.25.4)
Requires-Dist: mlflow (~=1.7.0)
Requires-Dist: mlflow-faculty (>=0.5.0)
